token_config.mdx
openai_image_token_counter/__init__.py
openai_image_token_counter/calculator.py
openai_image_token_counter/calculators.py
openai_image_token_counter/cli.py
openai_image_token_counter/config_loader.py
openai_image_token_counter/models.py
openai_image_token_counter/utils.py
openai_image_token_counter-1.0.0.dist-info/licenses/LICENSE
openai_image_token_counter-1.0.0.dist-info/METADATA
openai_image_token_counter-1.0.0.dist-info/WHEEL
openai_image_token_counter-1.0.0.dist-info/entry_points.txt
openai_image_token_counter-1.0.0.dist-info/top_level.txt
openai_image_token_counter-1.0.0.dist-info/RECORD
