Metadata-Version: 2.4
Name: openai-image-token-counter
Version: 1.0.0
Summary: Calculate token costs for images in OpenAI Vision API
Home-page: https://github.com/edujbarrios/openai-image-token-counter
Author: Eduardo J. Barrios
Author-email: "Eduardo J. Barrios" <contact@edujbarrios.com>
Maintainer-email: "Eduardo J. Barrios" <contact@edujbarrios.com>
License: MIT License
Project-URL: Homepage, https://github.com/edujbarrios/openai-image-token-counter
Project-URL: Bug Reports, https://github.com/edujbarrios/openai-image-token-counter/issues
Project-URL: Source, https://github.com/edujbarrios/openai-image-token-counter
Project-URL: Documentation, https://github.com/edujbarrios/openai-image-token-counter#readme
Keywords: openai,vision,api,tokens,image,calculator,cost,estimation
Classifier: Development Status :: 5 - Production/Stable
Classifier: Intended Audience :: Developers
Classifier: License :: OSI Approved :: MIT License
Classifier: Operating System :: OS Independent
Classifier: Programming Language :: Python :: 3
Classifier: Programming Language :: Python :: 3.7
Classifier: Programming Language :: Python :: 3.8
Classifier: Programming Language :: Python :: 3.9
Classifier: Programming Language :: Python :: 3.10
Classifier: Programming Language :: Python :: 3.11
Classifier: Programming Language :: Python :: 3.12
Classifier: Topic :: Software Development :: Libraries :: Python Modules
Classifier: Topic :: Scientific/Engineering :: Artificial Intelligence
Classifier: Topic :: Internet :: WWW/HTTP :: Dynamic Content
Requires-Python: >=3.7
License-File: LICENSE
Requires-Dist: Pillow>=8.0.0
Requires-Dist: PyYAML>=5.4.0
Provides-Extra: dev
Requires-Dist: pytest>=6.0; extra == "dev"
Requires-Dist: pytest-cov>=2.0; extra == "dev"
Requires-Dist: black>=21.0; extra == "dev"
Requires-Dist: flake8>=3.8; extra == "dev"
Requires-Dist: mypy>=0.800; extra == "dev"
Requires-Dist: build>=0.7.0; extra == "dev"
Requires-Dist: twine>=3.4.0; extra == "dev"
Dynamic: author
Dynamic: home-page
Dynamic: license-file
Dynamic: requires-python
